flask_scram.py
flask_scram-1.0.1.dist-info/LICENSE
flask_scram-1.0.1.dist-info/METADATA
flask_scram-1.0.1.dist-info/WHEEL
flask_scram-1.0.1.dist-info/top_level.txt
flask_scram-1.0.1.dist-info/RECORD
