Metadata-Version: 2.1
Name: flask-scram
Version: 1.0.1
Summary: Implements RFC 7804 Salted Challenge Response (SCRAM) HTTP Authentication Mechanism for the Flask web framework.
Author-email: Michael de Villiers <michael@devilears.co.za>
Maintainer-email: Michael de Villiers <michael@devilears.co.za>
License: MIT
Project-URL: Homepage, https://github.com/COUR4G3/flask-scram/
Project-URL: Source Code, https://github.com/COUR4G3/flask-scram/
Project-URL: Issue Tracker, https://github.com/COUR4G3/flask-scram/issues/
Classifier: Development Status :: 4 - Beta
Classifier: Environment :: Web Environment
Classifier: Intended Audience :: Developers
Classifier: License :: OSI Approved :: MIT License
Classifier: Operating System :: OS Independent
Classifier: Programming Language :: Python
Classifier: Topic :: Internet :: WWW/HTTP :: Dynamic Content
Requires-Python: >=3.8
License-File: LICENSE
Requires-Dist: flask
Requires-Dist: scramp
